ttsdb_tortoise/__init__.py
ttsdb_tortoise/config.yaml
ttsdb_tortoise/_vendor/source/.gitignore
ttsdb_tortoise/_vendor/source/Advanced_Usage.md
ttsdb_tortoise/_vendor/source/CHANGELOG.md
ttsdb_tortoise/_vendor/source/CITATION.cff
ttsdb_tortoise/_vendor/source/Dockerfile
ttsdb_tortoise/_vendor/source/LICENSE
ttsdb_tortoise/_vendor/source/MANIFEST.in
ttsdb_tortoise/_vendor/source/README.md
ttsdb_tortoise/_vendor/source/requirements.txt
ttsdb_tortoise/_vendor/source/setup.cfg
ttsdb_tortoise/_vendor/source/setup.py
ttsdb_tortoise/_vendor/source/tortoise_tts.ipynb
ttsdb_tortoise/_vendor/source/tortoise_v2_examples.html
ttsdb_tortoise/_vendor/source/voice_customization_guide.md
ttsdb_tortoise/_vendor/source/.github/workflows
ttsdb_tortoise/_vendor/source/examples/favorite_riding_hood.mp3
ttsdb_tortoise/_vendor/source/examples/favorites/atkins_mha.mp3
ttsdb_tortoise/_vendor/source/examples/favorites/atkins_omicron.mp3
ttsdb_tortoise/_vendor/source/examples/favorites/atkins_value.mp3
ttsdb_tortoise/_vendor/source/examples/favorites/daniel_craig_dumbledore.mp3
ttsdb_tortoise/_vendor/source/examples/favorites/daniel_craig_training_ethics.mp3
ttsdb_tortoise/_vendor/source/examples/favorites/dotrice_stop_for_death.mp3
ttsdb_tortoise/_vendor/source/examples/favorites/emma_stone_courage.mp3
ttsdb_tortoise/_vendor/source/examples/favorites/emma_stone_training_ethics.mp3
ttsdb_tortoise/_vendor/source/examples/favorites/halle_barry_dumbledore.mp3
ttsdb_tortoise/_vendor/source/examples/favorites/halle_barry_oar_to_oar.mp3
ttsdb_tortoise/_vendor/source/examples/favorites/henry_cavill_metallic_hydrogen.mp3
ttsdb_tortoise/_vendor/source/examples/favorites/kennard_road_not_taken.mp3
ttsdb_tortoise/_vendor/source/examples/favorites/morgan_freeman_metallic_hydrogen.mp3
ttsdb_tortoise/_vendor/source/examples/favorites/myself_gatsby.mp3
ttsdb_tortoise/_vendor/source/examples/favorites/patrick_stewart_omicron.mp3
ttsdb_tortoise-0.1.1.dist-info/METADATA
ttsdb_tortoise-0.1.1.dist-info/WHEEL
ttsdb_tortoise-0.1.1.dist-info/RECORD
